viresclient/__init__.py
viresclient/_client.py
viresclient/_client_aeolus.py
viresclient/_client_swarm.py
viresclient/_config.py
viresclient/_data_handling.py
viresclient/_api/__init__.py
viresclient/_api/token.py
viresclient/_api/upload.py
viresclient/_data/__init__.py
viresclient/_data/config_aeolus.json
viresclient/_data/config_swarm.json
viresclient/_wps/__init__.py
viresclient/_wps/environment.py
viresclient/_wps/http_util.py
viresclient/_wps/log_util.py
viresclient/_wps/multipart.py
viresclient/_wps/time_util.py
viresclient/_wps/wps.py
viresclient/_wps/wps_vires.py
viresclient/_wps/templates/model_eval_multipart_payload.xml
viresclient/_wps/templates/vires_aeolus_fetch_filtered_data.xml
viresclient/_wps/templates/vires_aeolus_fetch_filtered_data_async.xml
viresclient/_wps/templates/vires_fetch_filtered_data.xml
viresclient/_wps/templates/vires_fetch_filtered_data_async.xml
viresclient/_wps/templates/vires_getTimeData.xml
viresclient/_wps/templates/vires_get_collection_info.xml
viresclient/_wps/templates/vires_get_conjunctions.xml
viresclient/_wps/templates/vires_get_model_info.xml
viresclient/_wps/templates/vires_get_observatories.xml
viresclient/_wps/templates/vires_list_jobs.xml
viresclient/_wps/templates/vires_remove_job.xml
viresclient/_wps/templates/vires_times_from_orbits.xml
viresclient/commands/__init__.py
viresclient/commands/common.py
viresclient/commands/configuration.py
viresclient/commands/upload.py
viresclient/commands/viresclient.py
viresclient-0.14.1.dist-info/entry_points.txt
viresclient-0.14.1.dist-info/licenses/LICENSE
viresclient-0.14.1.dist-info/WHEEL
viresclient-0.14.1.dist-info/METADATA
viresclient-0.14.1.dist-info/RECORD
