Metadata-Version: 2.4
Name: viresclient
Version: 0.14.1
Summary: A Python client for interacting with a VirES server
Author-email: Ashley Smith <ashley.smith@ed.ac.uk>
Maintainer-email: Ashley Smith <ashley.smith@ed.ac.uk>
Requires-Python: >=3.7
Classifier: License :: OSI Approved :: MIT License
Classifier: Topic :: Scientific/Engineering
Classifier: Intended Audience :: Science/Research
Classifier: Intended Audience :: Developers
Classifier: Operating System :: OS Independent
Classifier: Programming Language :: Python
Classifier: Programming Language :: Python :: 3
Classifier: Programming Language :: Python :: 3.9
Classifier: Programming Language :: Python :: 3.10
Classifier: Programming Language :: Python :: 3.11
Classifier: Programming Language :: Python :: 3.12
Classifier: Programming Language :: Python :: 3.13
Classifier: Development Status :: 5 - Production/Stable
License-File: LICENSE
Requires-Dist: cdflib >= 0.3.9
Requires-Dist: h5py >= 3.12.1
Requires-Dist: Jinja2 >= 2.10
Requires-Dist: netCDF4 >= 1.5.3; python_version>='3.8'
Requires-Dist: netCDF4 >= 1.5.3, <= 1.5.8; python_version<='3.7'
Requires-Dist: pandas >= 0.18
Requires-Dist: requests >= 2.0.0
Requires-Dist: tables >= 3.4.4
Requires-Dist: tqdm >= 4.23.0
Requires-Dist: xarray >= 0.11.0
Requires-Dist: pytest >=6 ; extra == "dev"
Requires-Dist: nox >=2022 ; extra == "dev"
Requires-Dist: Sphinx == 8.2 ; extra == "docs"
Requires-Dist: sphinx-book-theme == 1.1.4 ; extra == "docs"
Requires-Dist: sphinx-copybutton == 0.5.2 ; extra == "docs"
Requires-Dist: sphinx-tabs == 3.4.7 ; extra == "docs"
Requires-Dist: pytest >=6 ; extra == "test"
Project-URL: homepage, https://github.com/ESA-VirES/VirES-Python-Client
Provides-Extra: dev
Provides-Extra: docs
Provides-Extra: test
